Marvel_API_HARI/Marvel_API_HARI.py
Marvel_API_HARI/__init__.py
Marvel_API_HARI-1.0.dist-info/METADATA
Marvel_API_HARI-1.0.dist-info/WHEEL
Marvel_API_HARI-1.0.dist-info/top_level.txt
Marvel_API_HARI-1.0.dist-info/RECORD
