Metadata-Version: 2.1
Name: Marvel-API-HARI
Version: 1.0
Summary: Package to fetch Marvel characters and perform filtering operations
Home-page: UNKNOWN
Author: Hari Dev S Aiyar
Author-email: aiyarhari@gmail.com
License: UNKNOWN
Platform: UNKNOWN
Classifier: Programming Language :: Python :: 3
Classifier: License :: OSI Approved :: MIT License
Classifier: Operating System :: OS Independent
Requires-Python: >=3.7
